LICENSE
README.md
setup.cfg
setup.py
src/pyconnectwise/__init__.py
src/pyconnectwise/config.py
src/pyconnectwise/exceptions.py
src/pyconnectwise/interfaces.py
src/pyconnectwise/types.py
src/pyconnectwise.egg-info/PKG-INFO
src/pyconnectwise.egg-info/SOURCES.txt
src/pyconnectwise.egg-info/dependency_links.txt
src/pyconnectwise.egg-info/requires.txt
src/pyconnectwise.egg-info/top_level.txt
src/pyconnectwise/clients/__init__.py
src/pyconnectwise/clients/automate_client.py
src/pyconnectwise/clients/connectwise_client.py
src/pyconnectwise/clients/manage_client.py
src/pyconnectwise/endpoints/__init__.py
src/pyconnectwise/endpoints/automate/ApitokenEndpoint.py
src/pyconnectwise/endpoints/automate/ApprovalpoliciesEndpoint.py
src/pyconnectwise/endpoints/automate/AvtemplatepoliciesEndpoint.py
src/pyconnectwise/endpoints/automate/AvtemplatepolicydataEndpoint.py
src/pyconnectwise/endpoints/automate/ClientsEndpoint.py
src/pyconnectwise/endpoints/automate/ClientsIdDocumentsEndpoint.py
src/pyconnectwise/endpoints/automate/ClientsIdEndpoint.py
src/pyconnectwise/endpoints/automate/ClientsIdLicensesEndpoint.py
src/pyconnectwise/endpoints/automate/ClientsIdPermissionsEndpoint.py
src/pyconnectwise/endpoints/automate/ClientsIdPermissionsIdEndpoint.py
src/pyconnectwise/endpoints/automate/ClientsIdProductkeysEndpoint.py
src/pyconnectwise/endpoints/automate/CommandsEndpoint.py
src/pyconnectwise/endpoints/automate/CommandsIdEndpoint.py
src/pyconnectwise/endpoints/automate/ComputermenusEndpoint.py
src/pyconnectwise/endpoints/automate/ComputersChassisEndpoint.py
src/pyconnectwise/endpoints/automate/ComputersDrivesEndpoint.py
src/pyconnectwise/endpoints/automate/ComputersEndpoint.py
src/pyconnectwise/endpoints/automate/ComputersIdAlertsEndpoint.py
src/pyconnectwise/endpoints/automate/ComputersIdAlertsuspensionsEndpoint.py
src/pyconnectwise/endpoints/automate/ComputersIdAlertsuspensionsMaintenancewindowEndpoint.py
src/pyconnectwise/endpoints/automate/ComputersIdAlertsuspensionsTemplatediversionEndpoint.py
src/pyconnectwise/endpoints/automate/ComputersIdBiosEndpoint.py
src/pyconnectwise/endpoints/automate/ComputersIdCommandexecuteEndpoint.py
