Metadata-Version: 2.1
Name: pyconnectwise
Version: 0.5.0
Summary: A full-featured Python client for the ConnectWise API's
Home-page: https://github.com/HealthITAU/pyconnectwise
Author: Health IT
Author-email: dev@healthit.com.au
License: gpl-3.0
Keywords: ConnectWise,Manage,Automate,API,Python,Client,Annotated,Typed,MSP
Classifier: Development Status :: 4 - Beta
Classifier: Intended Audience :: Developers
Classifier: Topic :: Software Development :: Libraries :: Python Modules
Classifier: License :: OSI Approved :: GNU General Public License v3 or later (GPLv3+)
Classifier: Programming Language :: Python :: 3.11
Classifier: Programming Language :: Python :: 3.10
Requires-Python: >=3.10.1
License-File: LICENSE
